blinky/__init__.py
blinky/settings.py
blinky/urls.py
blinky/wsgi.py
blinky-1.1.1.dist-info/top_level.txt
blinky-1.1.1.dist-info/METADATA
blinky-1.1.1.dist-info/DESCRIPTION.rst
blinky-1.1.1.dist-info/metadata.json
blinky-1.1.1.dist-info/WHEEL
blinky-1.1.1.dist-info/RECORD
